play_mqtt/__init__.py
play_mqtt/providers.py
play_mqtt-0.0.5.dist-info/LICENSE
play_mqtt-0.0.5.dist-info/METADATA
play_mqtt-0.0.5.dist-info/WHEEL
play_mqtt-0.0.5.dist-info/entry_points.txt
play_mqtt-0.0.5.dist-info/top_level.txt
play_mqtt-0.0.5.dist-info/RECORD
