Metadata-Version: 2.1
Name: play-mqtt
Version: 0.0.5
Summary: pytest-play support for MQTT
Home-page: https://github.com/davidemoro/play_mqtt
Author: Davide Moro
Author-email: davide.moro@gmail.com
License: Apache Software License 2.0
Keywords: play_mqtt
Platform: UNKNOWN
Classifier: Development Status :: 2 - Pre-Alpha
Classifier: Intended Audience :: Developers
Classifier: License :: OSI Approved :: Apache Software License
Classifier: Natural Language :: English
Classifier: Programming Language :: Python :: 2
Classifier: Programming Language :: Python :: 2.6
Classifier: Programming Language :: Python :: 2.7
Classifier: Programming Language :: Python :: 3
Classifier: Programming Language :: Python :: 3.3
Classifier: Programming Language :: Python :: 3.4
Classifier: Programming Language :: Python :: 3.5
Requires-Dist: paho-mqtt
Requires-Dist: pytest-play (>=2.0.0)
Provides-Extra: tests
Requires-Dist: pytest ; extra == 'tests'
Requires-Dist: mock ; extra == 'tests'
Requires-Dist: pytest-cov ; extra == 'tests'
